{
  "AL": { "name": "Alabama", "base_multiplier": 0.85, "permitFee": { "min": 200, "max": 450 }},
  "AK": { "name": "Alaska", "base_multiplier": 1.4, "permitFee": { "min": 500, "max": 1200 }},
  "AZ": { "name": "Arizona", "base_multiplier": 0.95, "permitFee": { "min": 400, "max": 800 }},
  "AR": { "name": "Arkansas", "base_multiplier": 0.8, "permitFee": { "min": 200, "max": 400 }},
  "CA": { "name": "California", "base_multiplier": 1.3, "permitFee": { "min": 800, "max": 2500 }, "regions": { "90000-93599": 1.15, "94000-95199": 1.2, "default": 1.0 }},
  "CO": { "name": "Colorado", "base_multiplier": 1.05, "permitFee": { "min": 600, "max": 1200 }},
  "CT": { "name": "Connecticut", "base_multiplier": 1.2, "permitFee": { "min": 500, "max": 1000 }},
  "DE": { "name": "Delaware", "base_multiplier": 1.0, "permitFee": { "min": 400, "max": 700 }},
  "DC": { "name": "District of Columbia", "base_multiplier": 1.4, "permitFee": { "min": 1000, "max": 2000 }},
  "FL": { "name": "Florida", "base_multiplier": 1.0, "permitFee": { "min": 400, "max": 750 }},
  "GA": { "name": "Georgia", "base_multiplier": 0.9, "permitFee": { "min": 350, "max": 600 }},
  "HI": { "name": "Hawaii", "base_multiplier": 1.5, "permitFee": { "min": 800, "max": 1500 }},
  "ID": { "name": "Idaho", "base_multiplier": 0.95, "permitFee": { "min": 300, "max": 600 }},
  "IL": { "name": "Illinois", "base_multiplier": 1.1, "permitFee": { "min": 500, "max": 900 }},
  "IN": { "name": "Indiana", "base_multiplier": 0.9, "permitFee": { "min": 300, "max": 500 }},
  "IA": { "name": "Iowa", "base_multiplier": 0.9, "permitFee": { "min": 250, "max": 450 }},
  "KS": { "name": "Kansas", "base_multiplier": 0.9, "permitFee": { "min": 200, "max": 400 }},
  "KY": { "name": "Kentucky", "base_multiplier": 0.85, "permitFee": { "min": 250, "max": 500 }},
  "LA": { "name": "Louisiana", "base_multiplier": 0.9, "permitFee": { "min": 150, "max": 350 }},
  "ME": { "name": "Maine", "base_multiplier": 1.1, "permitFee": { "min": 400, "max": 800 }},
  "MD": { "name": "Maryland", "base_multiplier": 1.2, "permitFee": { "min": 700, "max": 1500 }},
  "MA": { "name": "Massachusetts", "base_multiplier": 1.3, "permitFee": { "min": 800, "max": 1800 }},
  "MI": { "name": "Michigan", "base_multiplier": 1.0, "permitFee": { "min": 400, "max": 900 }},
  "MN": { "name": "Minnesota", "base_multiplier": 1.1, "permitFee": { "min": 500, "max": 1000 }},
  "MS": { "name": "Mississippi", "base_multiplier": 0.8, "permitFee": { "min": 150, "max": 300 }},
  "MO": { "name": "Missouri", "base_multiplier": 0.9, "permitFee": { "min": 250, "max": 500 }},
  "MT": { "name": "Montana", "base_multiplier": 1.0, "permitFee": { "min": 400, "max": 700 }},
  "NE": { "name": "Nebraska", "base_multiplier": 0.9, "permitFee": { "min": 200, "max": 400 }},
  "NV": { "name": "Nevada", "base_multiplier": 1.05, "permitFee": { "min": 400, "max": 900 }},
  "NH": { "name": "New Hampshire", "base_multiplier": 1.15, "permitFee": { "min": 500, "max": 1100 }},
  "NJ": { "name": "New Jersey", "base_multiplier": 1.25, "permitFee": { "min": 800, "max": 1600 }},
  "NM": { "name": "New Mexico", "base_multiplier": 0.9, "permitFee": { "min": 300, "max": 600 }},
  "NY": { "name": "New York", "base_multiplier": 1.2, "permitFee": { "min": 600, "max": 1500 }, "regions": { "10000-11999": 1.25, "default": 1.0 }},
  "NC": { "name": "North Carolina", "base_multiplier": 0.9, "permitFee": { "min": 300, "max": 700 }},
  "ND": { "name": "North Dakota", "base_multiplier": 0.95, "permitFee": { "min": 300, "max": 500 }},
  "OH": { "name": "Ohio", "base_multiplier": 0.95, "permitFee": { "min": 400, "max": 800 }},
  "OK": { "name": "Oklahoma", "base_multiplier": 0.85, "permitFee": { "min": 250, "max": 450 }},
  "OR": { "name": "Oregon", "base_multiplier": 1.1, "permitFee": { "min": 700, "max": 1400 }},
  "PA": { "name": "Pennsylvania", "base_multiplier": 1.05, "permitFee": { "min": 500, "max": 1000 }},
  "RI": { "name": "Rhode Island", "base_multiplier": 1.15, "permitFee": { "min": 600, "max": 1200 }},
  "SC": { "name": "South Carolina", "base_multiplier": 0.85, "permitFee": { "min": 300, "max": 600 }},
  "SD": { "name": "South Dakota", "base_multiplier": 0.9, "permitFee": { "min": 200, "max": 400 }},
  "TN": { "name": "Tennessee", "base_multiplier": 0.85, "permitFee": { "min": 300, "max": 550 }},
  "TX": { "name": "Texas", "base_multiplier": 0.9, "permitFee": { "min": 300, "max": 600 }},
  "UT": { "name": "Utah", "base_multiplier": 1.0, "permitFee": { "min": 500, "max": 1000 }},
  "VT": { "name": "Vermont", "base_multiplier": 1.15, "permitFee": { "min": 500, "max": 900 }},
  "VA": { "name": "Virginia", "base_multiplier": 1.0, "permitFee": { "min": 450, "max": 850 }},
  "WA": { "name": "Washington", "base_multiplier": 1.15, "permitFee": { "min": 700, "max": 1500 }},
  "WV": { "name": "West Virginia", "base_multiplier": 0.85, "permitFee": { "min": 200, "max": 400 }},
  "WI": { "name": "Wisconsin", "base_multiplier": 1.05, "permitFee": { "min": 450, "max": 950 }},
  "WY": { "name": "Wyoming", "base_multiplier": 1.0, "permitFee": { "min": 400, "max": 700 }},
  "default": { "name": "Average (US)", "base_multiplier": 1.0, "permitFee": { "min": 450, "max": 900 }}
}